mercadobitcoin/__init__.py
mercadobitcoin/api.py
mercadobitcoin/errors.py
mercadobitcoin/trade_api.py
mercadobitcoin-0.6.0.dist-info/LICENSE
mercadobitcoin-0.6.0.dist-info/METADATA
mercadobitcoin-0.6.0.dist-info/WHEEL
mercadobitcoin-0.6.0.dist-info/top_level.txt
mercadobitcoin-0.6.0.dist-info/RECORD
