Metadata-Version: 2.1
Name: mercadobitcoin
Version: 0.6.0
Summary: A Python wrapper for Mercado Bitcoin API
Home-page: https://github.com/alfakini/python-mercadobitcoin
Author: Alan Fachini
Author-email: alfakini@gmail.com
License: UNKNOWN
Download-URL: https://github.com/alfakini/python-mercadobitcoin/tarball/0.6.0
Keywords: bitcoin,litcoin,ethereum,ripple,mercadobitcoin,trade,orderbook
Platform: UNKNOWN
Classifier: Development Status :: 4 - Beta
Classifier: Environment :: Console
Classifier: Intended Audience :: Customer Service
Classifier: Intended Audience :: Financial and Insurance Industry
Classifier: Intended Audience :: Developers
Classifier: Intended Audience :: Science/Research
Classifier: License :: OSI Approved :: MIT License
Classifier: Natural Language :: English
Classifier: Operating System :: OS Independent
Classifier: Programming Language :: Python :: 2.7
Classifier: Programming Language :: Python :: 3.7
Classifier: Topic :: Software Development :: Libraries :: Python Modules
Classifier: Topic :: Utilities
Requires-Dist: requests
